[
	{
		"__TYPE__": "SharedSliceContent",
		"variation": "default",
		"primary": {
			"cta_link": {
				"__TYPE__": "LinkContent",
				"value": {
					"__TYPE__": "ExternalLink",
					"url": "http://twitter.com"
				}
			},
			"cta_link_label": {
				"__TYPE__": "FieldContent",
				"value": "from",
				"type": "Text"
			},
			"paragraph": {
				"__TYPE__": "StructuredTextContent",
				"value": [
					{
						"type": "paragraph",
						"content": {
							"text": "Magna ea quis amet velit commodo reprehenderit excepteur mollit excepteur eiusmod."
						}
					}
				]
			},
			"paragraph_second": {
				"__TYPE__": "StructuredTextContent",
				"value": [
					{
						"type": "paragraph",
						"content": {
							"text": "Quis duis anim ex Lorem incididunt ea ipsum cupidatat elit laboris aliquip quis."
						}
					}
				]
			},
			"title": {
				"__TYPE__": "StructuredTextContent",
				"value": [
					{
						"type": "heading1",
						"content": {
							"text": "Writing"
						}
					}
				]
			}
		},
		"items": []
	}
]
